LICENSE
MANIFEST.in
README.rst
setup.py
tox.ini
traceback/__init__.py
traceback/tests.py
tracefront.egg-info/PKG-INFO
tracefront.egg-info/SOURCES.txt
tracefront.egg-info/dependency_links.txt
tracefront.egg-info/requires.txt
tracefront.egg-info/top_level.txt