Metadata-Version: 1.0
Name: tracefront
Version: 0.1
Summary: Format tracebacks better.
Home-page: https://github.com/erikrose/tracefront
Author: Erik Rose
Author-email: erikrose@grinchcentral.com
License: MIT
Keywords: traceback,exception,frame,stack
Platform: UNKNOWN
Classifier: Development Status :: 2 - Pre-Alpha
Classifier: Intended Audience :: Developers
Classifier: Natural Language :: English
Classifier: License :: OSI Approved :: MIT License
Classifier: Programming Language :: Python :: 2
Classifier: Programming Language :: Python :: 2.5
Classifier: Programming Language :: Python :: 2.6
Classifier: Programming Language :: Python :: 2.7
Classifier: Topic :: Software Development :: Libraries
Classifier: Topic :: Software Development :: User Interfaces
